simple5ploit/__init__.py
simple5ploit/__main__.py
simple5ploit/modules/__init__.py
simple5ploit/modules/exploits/bludit_brute_force_mitigation_bypass.py
simple5ploit/modules/exploits/samba_usermap_script.py
simple5ploit/modules/exploits/shellshock.py
simple5ploit/modules/exploits/internal/base.py
simple5ploit/modules/exploits/internal/cli.py
simple5ploit/modules/gather/get_http_headers.py
simple5ploit/modules/gather/nmap_os_detection.py
simple5ploit/modules/gather/nmap_scan_top_ports.py
simple5ploit/modules/gather/nmap_subnet_scan.py
simple5ploit/modules/gather/nmap_version_detection.py
simple5ploit/modules/gather/zerologon_check.py
simple5ploit/modules/gather/internal/base.py
simple5ploit/modules/gather/internal/cli.py
simple5ploit/utils/server.py
simple5ploit-1.0.2.dist-info/entry_points.txt
simple5ploit-1.0.2.dist-info/LICENSE
simple5ploit-1.0.2.dist-info/WHEEL
simple5ploit-1.0.2.dist-info/METADATA
simple5ploit-1.0.2.dist-info/RECORD
