Metadata-Version: 2.1
Name: simple5ploit
Version: 1.0.2
Summary: simple5ploit
Home-page: https://github.com/binexisHATT/simple5ploit
License: UNKNOWN
Author: Alexis Rodriguez
Author-email: rodriguez10011999@gmail.com
Classifier: License :: OSI Approved :: MIT License
Requires-Dist: prompt_toolkit
Requires-Dist: tabulate
Requires-Dist: python3-nmap
